Workbook
Name 品类_01: #REF!
Name 品类_01: #REF!
Name 品类_01: #REF!

Sheet 展示用-2026年签约数据汇总（0702统计）
A2: 组别 | B2: 序号 | C2: 人员 | D2: 客户简称 | E2: 销售产品名称/项目名称 | F2: 落地地点 | G2: 客户来源 （展会需注明） | H2: 备注 | I2: 签约后且收到第一笔款后才算已签约
I3: 1月 | J3: 2月 | K3: 3月 | L3: 4月 | M3: 5月 | N3: 6月 | O3: 7月 | P3: 8月 | Q3: 9月 | R3: 10月 | S3: 11月 | T3: 12月
A4: 傲翔组 | B4: 1 | C4: A | D4: B | E4: C | F4: D | G4: E | H4: F | J4: 500000
B5: 2 | C5: A | D5: G | E5: H | F5: I | G5: J | H5: K | M5: 780000
B6: 3 | C6: A | D6: L | E6: M | F6: N | G6: O | H6: P | N6: 450000
B7: 4 | C7: A | D7: Q | E7: R | F7: S | G7: T | H7: U | O7: 68000
B8: 个人月度合计： | I8: =SUM(I4:I7) | J8: =SUM(J4:J7) | K8: =SUM(K4:K7) | L8: =SUM(L4:L7) | M8: =SUM(M4:M7) | N8: =SUM(N4:N7) | O8: =SUM(O4:O7) | P8: =SUM(P4:P7) | ... T8: =SUM(T4:T7)
B9: 个人季度合计： | I9: =SUM(I8:K8) | L9: =SUM(L8:N8) | O9: =SUM(O8:Q8) | R9: =SUM(R8:T8)
B10: 个人年度合计： | I10: =SUM(I8:T8)
B11: 小组月度合计： | I11: =SUM(I8) | J11: =SUM(J8) | K11: =SUM(K8) | L11: =SUM(L8) | M11: =SUM(M8) | N11: =SUM(N8) | O11: =SUM(O8) | P11: =SUM(P8) | ... T11: =SUM(T8)
B12: 小组季度合计： | I12: =SUM(I11:K11) | L12: =SUM(L11:N11) | O12: =SUM(O11:Q11) | R12: =SUM(R11:T11)
B13: 小组年度合计： | I13: =SUM(I11:T11)
A15: 冉哥组 | B15: 1 | C15: B | D15: B | E15: C | F15: D | G15: E | H15: F | J15: 500000
B16: 2 | C16: B | D16: G | E16: H | F16: I | G16: J | H16: K | M16: 780000
B17: 3 | C17: B | D17: L | E17: M | F17: N | G17: O | H17: P | K17: 600000 | N17: 450000
B18: 4 | C18: B | D18: Q | E18: R | F18: S | G18: T | H18: U | O18: 68000
B19: 个人月度合计： | I19: =SUM(I15:I18) | J19: =SUM(J15:J18) | K19: =SUM(K15:K18) | L19: =SUM(L15:L18) | M19: =SUM(M15:M18) | N19: =SUM(N15:N18) | O19: =SUM(O15:O18) | P19: =SUM(P15:P18) | ... T19: =SUM(T15:T18)
B20: 个人季度合计： | I20: =SUM(I19:K19) | L20: =SUM(L19:N19) | O20: =SUM(O19:Q19) | R20: =SUM(R19:T19)
B21: 个人年度合计： | I21: =SUM(I19:T19)
B22: 小组月度合计： | I22: =SUM(I19) | J22: =SUM(J19) | K22: =SUM(K19) | L22: =SUM(L19) | M22: =SUM(M19) | N22: =SUM(N19) | O22: =SUM(O19) | P22: =SUM(P19) | ... T22: =SUM(T19)
B23: 小组季度合计： | I23: =SUM(I22:K22) | L23: =SUM(L22:N22) | O23: =SUM(O22:Q22) | R23: =SUM(R22:T22)
B24: 小组年度合计： | I24: =SUM(I22:T22)
A25: 部门月度合计： | I25: =SUM(I11,I22) | J25: =SUM(J11,J22) | K25: =SUM(K11,K22) | L25: =SUM(L11,L22) | M25: =SUM(M11,M22) | N25: =SUM(N11,N22) | O25: =SUM(O11,O22) | P25: =SUM(P11,P22) | ... T25: =SUM(T11,T22)
A26: 部门季度合计： | I26: =SUM(I25:K25) | L26: =SUM(L25:N25) | O26: =SUM(O25:Q25) | R26: =SUM(R25:T25)
A27: 部门年度合计： | I27: =SUM(I25:T25)

Sheet 展示用-签约排名汇总（0702统计）
C2: 已签约统计数据表
B3: 签约后且收到第一笔款后才算已签约
B4: 组别 | C4: 人员 | D4: 1月 | E4: 2月 | F4: 3月 | G4: 4月 | H4: 5月 | I4: 6月 | J4: 7月 | K4: 8月 | L4: 9月 | M4: 10月 | N4: 11月 | O4: 12月 | P4: 总计
B5: 勇哥组 | C5: 庄志勇 | D5: =SUMIF('展示用-2026年签约数据汇总（0702统计）'!C:C,C5,'展示用-2026年签约数据汇总（0702统计）'!I:I) | E5: =SUMIF('展示用-2026年签约数据汇总（0702统计）'!C:C,C5,'展示用-2026年签约数据汇总（0702统计）'!J:J) | F5: =SUMIF('展示用-2026年签约数据汇总（0702统计）'!C:C,C5,'展示用-2026年签约数据汇总（0702统计）'!K:K) | G5: =SUMIF('展示用-2026年签约数据汇总（0702统计）'!C:C,C5,'展示用-2026年签约数据汇总（0702统计）'!L:L) | H5: =SUMIF('展示用-2026年签约数据汇总（0702统计）'!C:C,C5,'展示用-2026年签约数据汇总（0702统计）'!M:M) | I5: =SUMIF('展示用-2026年签约数据汇总（0702统计）'!C:C,C5,'展示用-2026年签约数据汇总（0702统计）'!N:N) | P5: =SUM(D5:O5)
C6: 曾锦鹏 | D6: / | E6: / | F6: / | G6: / | H6: / | I6: =SUMIF('展示用-2026年签约数据汇总（0702统计）'!C:C,C6,'展示用-2026年签约数据汇总（0702统计）'!N:N) | P6: =SUM(D6:O6)
C7: 李敏健 | D7: / | E7: / | F7: / | G7: / | H7: / | I7: =SUMIF('展示用-2026年签约数据汇总（0702统计）'!C:C,C7,'展示用-2026年签约数据汇总（0702统计）'!N:N) | P7: =SUM(D7:O7)
C8: 毕亚吉 | D8: =SUMIF('展示用-2026年签约数据汇总（0702统计）'!C:C,C8,'展示用-2026年签约数据汇总（0702统计）'!I:I) | E8: =SUMIF('展示用-2026年签约数据汇总（0702统计）'!C:C,C8,'展示用-2026年签约数据汇总（0702统计）'!J:J) | F8: =SUMIF('展示用-2026年签约数据汇总（0702统计）'!C:C,C8,'展示用-2026年签约数据汇总（0702统计）'!K:K) | G8: =SUMIF('展示用-2026年签约数据汇总（0702统计）'!C:C,C8,'展示用-2026年签约数据汇总（0702统计）'!L:L) | H8: =SUMIF('展示用-2026年签约数据汇总（0702统计）'!C:C,C8,'展示用-2026年签约数据汇总（0702统计）'!M:M) | I8: =SUMIF('展示用-2026年签约数据汇总（0702统计）'!C:C,C8,'展示用-2026年签约数据汇总（0702统计）'!N:N) | P8: =SUM(D8:O8)
C9: 吴祖陈 | D9: =SUMIF('展示用-2026年签约数据汇总（0702统计）'!C:C,C9,'展示用-2026年签约数据汇总（0702统计）'!I:I) | E9: =SUMIF('展示用-2026年签约数据汇总（0702统计）'!C:C,C9,'展示用-2026年签约数据汇总（0702统计）'!J:J) | F9: =SUMIF('展示用-2026年签约数据汇总（0702统计）'!C:C,C9,'展示用-2026年签约数据汇总（0702统计）'!K:K) | G9: =SUMIF('展示用-2026年签约数据汇总（0702统计）'!C:C,C9,'展示用-2026年签约数据汇总（0702统计）'!L:L) | H9: =SUMIF('展示用-2026年签约数据汇总（0702统计）'!C:C,C9,'展示用-2026年签约数据汇总（0702统计）'!M:M) | I9: =SUMIF('展示用-2026年签约数据汇总（0702统计）'!C:C,C9,'展示用-2026年签约数据汇总（0702统计）'!N:N) | P9: =SUM(D9:O9)
C10: 黄梓毅 | D10: / | E10: / | F10: / | G10: =SUMIF('展示用-2026年签约数据汇总（0702统计）'!C:C,C10,'展示用-2026年签约数据汇总（0702统计）'!L:L) | H10: =SUMIF('展示用-2026年签约数据汇总（0702统计）'!C:C,C10,'展示用-2026年签约数据汇总（0702统计）'!M:M) | I10: =SUMIF('展示用-2026年签约数据汇总（0702统计）'!C:C,C10,'展示用-2026年签约数据汇总（0702统计）'!N:N) | P10: =SUM(D10:O10)
C11: 林国斌 | D11: / | E11: / | F11: / | G11: =SUMIF('展示用-2026年签约数据汇总（0702统计）'!C:C,C11,'展示用-2026年签约数据汇总（0702统计）'!L:L) | H11: =SUMIF('展示用-2026年签约数据汇总（0702统计）'!C:C,C11,'展示用-2026年签约数据汇总（0702统计）'!M:M) | I11: =SUMIF('展示用-2026年签约数据汇总（0702统计）'!C:C,C11,'展示用-2026年签约数据汇总（0702统计）'!N:N) | P11: =SUM(D11:O11)
C12: 陈晓勇 | D12: / | E12: / | F12: / | G12: =SUMIF('展示用-2026年签约数据汇总（0702统计）'!C:C,C12,'展示用-2026年签约数据汇总（0702统计）'!L:L) | H12: =SUMIF('展示用-2026年签约数据汇总（0702统计）'!C:C,C12,'展示用-2026年签约数据汇总（0702统计）'!M:M) | I12: =SUMIF('展示用-2026年签约数据汇总（0702统计）'!C:C,C12,'展示用-2026年签约数据汇总（0702统计）'!N:N) | P12: =SUM(D12:O12)
C13: 李雷
C14: 梁秋霞
B15: 傲翔组 | C15: 吴傲翔 | D15: =SUMIF('展示用-2026年签约数据汇总（0702统计）'!C:C,C15,'展示用-2026年签约数据汇总（0702统计）'!I:I) | E15: =SUMIF('展示用-2026年签约数据汇总（0702统计）'!C:C,C15,'展示用-2026年签约数据汇总（0702统计）'!J:J) | F15: =SUMIF('展示用-2026年签约数据汇总（0702统计）'!C:C,C15,'展示用-2026年签约数据汇总（0702统计）'!K:K) | G15: =SUMIF('展示用-2026年签约数据汇总（0702统计）'!C:C,C15,'展示用-2026年签约数据汇总（0702统计）'!L:L) | H15: =SUMIF('展示用-2026年签约数据汇总（0702统计）'!C:C,C15,'展示用-2026年签约数据汇总（0702统计）'!M:M) | I15: =SUMIF('展示用-2026年签约数据汇总（0702统计）'!C:C,C15,'展示用-2026年签约数据汇总（0702统计）'!N:N) | P15: =SUM(D15:O15)
C16: 李菁萍 | D16: =SUMIF('展示用-2026年签约数据汇总（0702统计）'!C:C,C16,'展示用-2026年签约数据汇总（0702统计）'!I:I) | E16: =SUMIF('展示用-2026年签约数据汇总（0702统计）'!C:C,C16,'展示用-2026年签约数据汇总（0702统计）'!J:J) | F16: =SUMIF('展示用-2026年签约数据汇总（0702统计）'!C:C,C16,'展示用-2026年签约数据汇总（0702统计）'!K:K) | G16: =SUMIF('展示用-2026年签约数据汇总（0702统计）'!C:C,C16,'展示用-2026年签约数据汇总（0702统计）'!L:L) | H16: =SUMIF('展示用-2026年签约数据汇总（0702统计）'!C:C,C16,'展示用-2026年签约数据汇总（0702统计）'!M:M) | I16: =SUMIF('展示用-2026年签约数据汇总（0702统计）'!C:C,C16,'展示用-2026年签约数据汇总（0702统计）'!N:N) | P16: =SUM(D16:O16)
C17: 于永强 | D17: =SUMIF('展示用-2026年签约数据汇总（0702统计）'!C:C,C17,'展示用-2026年签约数据汇总（0702统计）'!I:I) | E17: =SUMIF('展示用-2026年签约数据汇总（0702统计）'!C:C,C17,'展示用-2026年签约数据汇总（0702统计）'!J:J) | F17: =SUMIF('展示用-2026年签约数据汇总（0702统计）'!C:C,C17,'展示用-2026年签约数据汇总（0702统计）'!K:K) | G17: =SUMIF('展示用-2026年签约数据汇总（0702统计）'!C:C,C17,'展示用-2026年签约数据汇总（0702统计）'!L:L) | H17: =SUMIF('展示用-2026年签约数据汇总（0702统计）'!C:C,C17,'展示用-2026年签约数据汇总（0702统计）'!M:M) | I17: =SUMIF('展示用-2026年签约数据汇总（0702统计）'!C:C,C17,'展示用-2026年签约数据汇总（0702统计）'!N:N) | P17: =SUM(D17:O17)
C18: 胡佳新 | D18: =SUMIF('展示用-2026年签约数据汇总（0702统计）'!C:C,C18,'展示用-2026年签约数据汇总（0702统计）'!I:I) | E18: =SUMIF('展示用-2026年签约数据汇总（0702统计）'!C:C,C18,'展示用-2026年签约数据汇总（0702统计）'!J:J) | F18: =SUMIF('展示用-2026年签约数据汇总（0702统计）'!C:C,C18,'展示用-2026年签约数据汇总（0702统计）'!K:K) | G18: =SUMIF('展示用-2026年签约数据汇总（0702统计）'!C:C,C18,'展示用-2026年签约数据汇总（0702统计）'!L:L) | H18: =SUMIF('展示用-2026年签约数据汇总（0702统计）'!C:C,C18,'展示用-2026年签约数据汇总（0702统计）'!M:M) | I18: =SUMIF('展示用-2026年签约数据汇总（0702统计）'!C:C,C18,'展示用-2026年签约数据汇总（0702统计）'!N:N) | P18: =SUM(D18:O18)
B19: 意林组 | C19: 杨意林 | D19: =SUMIF('展示用-2026年签约数据汇总（0702统计）'!C:C,C19,'展示用-2026年签约数据汇总（0702统计）'!I:I) | E19: =SUMIF('展示用-2026年签约数据汇总（0702统计）'!C:C,C19,'展示用-2026年签约数据汇总（0702统计）'!J:J) | F19: =SUMIF('展示用-2026年签约数据汇总（0702统计）'!C:C,C19,'展示用-2026年签约数据汇总（0702统计）'!K:K) | G19: =SUMIF('展示用-2026年签约数据汇总（0702统计）'!C:C,C19,'展示用-2026年签约数据汇总（0702统计）'!L:L) | H19: =SUMIF('展示用-2026年签约数据汇总（0702统计）'!C:C,C19,'展示用-2026年签约数据汇总（0702统计）'!M:M) | I19: =SUMIF('展示用-2026年签约数据汇总（0702统计）'!C:C,C19,'展示用-2026年签约数据汇总（0702统计）'!N:N) | P19: =SUM(D19:O19)
C20: 杨第洲 | D20: =SUMIF('展示用-2026年签约数据汇总（0702统计）'!C:C,C20,'展示用-2026年签约数据汇总（0702统计）'!I:I) | E20: =SUMIF('展示用-2026年签约数据汇总（0702统计）'!C:C,C20,'展示用-2026年签约数据汇总（0702统计）'!J:J) | F20: =SUMIF('展示用-2026年签约数据汇总（0702统计）'!C:C,C20,'展示用-2026年签约数据汇总（0702统计）'!K:K) | G20: =SUMIF('展示用-2026年签约数据汇总（0702统计）'!C:C,C20,'展示用-2026年签约数据汇总（0702统计）'!L:L) | H20: =SUMIF('展示用-2026年签约数据汇总（0702统计）'!C:C,C20,'展示用-2026年签约数据汇总（0702统计）'!M:M) | I20: =SUMIF('展示用-2026年签约数据汇总（0702统计）'!C:C,C20,'展示用-2026年签约数据汇总（0702统计）'!N:N) | P20: =SUM(D20:O20)
C21: 邬晓娟 | D21: =SUMIF('展示用-2026年签约数据汇总（0702统计）'!C:C,C21,'展示用-2026年签约数据汇总（0702统计）'!I:I) | E21: =SUMIF('展示用-2026年签约数据汇总（0702统计）'!C:C,C21,'展示用-2026年签约数据汇总（0702统计）'!J:J) | F21: =SUMIF('展示用-2026年签约数据汇总（0702统计）'!C:C,C21,'展示用-2026年签约数据汇总（0702统计）'!K:K) | G21: =SUMIF('展示用-2026年签约数据汇总（0702统计）'!C:C,C21,'展示用-2026年签约数据汇总（0702统计）'!L:L) | H21: =SUMIF('展示用-2026年签约数据汇总（0702统计）'!C:C,C21,'展示用-2026年签约数据汇总（0702统计）'!M:M) | I21: =SUMIF('展示用-2026年签约数据汇总（0702统计）'!C:C,C21,'展示用-2026年签约数据汇总（0702统计）'!N:N) | P21: =SUM(D21:O21)
C22: 钟嫄 | D22: =SUMIF('展示用-2026年签约数据汇总（0702统计）'!C:C,C22,'展示用-2026年签约数据汇总（0702统计）'!I:I) | E22: =SUMIF('展示用-2026年签约数据汇总（0702统计）'!C:C,C22,'展示用-2026年签约数据汇总（0702统计）'!J:J) | F22: =SUMIF('展示用-2026年签约数据汇总（0702统计）'!C:C,C22,'展示用-2026年签约数据汇总（0702统计）'!K:K) | G22: =SUMIF('展示用-2026年签约数据汇总（0702统计）'!C:C,C22,'展示用-2026年签约数据汇总（0702统计）'!L:L) | H22: =SUMIF('展示用-2026年签约数据汇总（0702统计）'!C:C,C22,'展示用-2026年签约数据汇总（0702统计）'!M:M) | I22: =SUMIF('展示用-2026年签约数据汇总（0702统计）'!C:C,C22,'展示用-2026年签约数据汇总（0702统计）'!N:N) | P22: =SUM(D22:O22)
B23: 冉哥组 | C23: 冉钦 | D23: =SUMIF('展示用-2026年签约数据汇总（0702统计）'!C:C,C23,'展示用-2026年签约数据汇总（0702统计）'!I:I) | E23: =SUMIF('展示用-2026年签约数据汇总（0702统计）'!C:C,C23,'展示用-2026年签约数据汇总（0702统计）'!J:J) | F23: =SUMIF('展示用-2026年签约数据汇总（0702统计）'!C:C,C23,'展示用-2026年签约数据汇总（0702统计）'!K:K) | G23: =SUMIF('展示用-2026年签约数据汇总（0702统计）'!C:C,C23,'展示用-2026年签约数据汇总（0702统计）'!L:L) | H23: =SUMIF('展示用-2026年签约数据汇总（0702统计）'!C:C,C23,'展示用-2026年签约数据汇总（0702统计）'!M:M) | I23: =SUMIF('展示用-2026年签约数据汇总（0702统计）'!C:C,C23,'展示用-2026年签约数据汇总（0702统计）'!N:N) | P23: =SUM(D23:O23)
B24: 王安祥组 | C24: 王安祥 | D24: =SUMIF('展示用-2026年签约数据汇总（0702统计）'!C:C,C24,'展示用-2026年签约数据汇总（0702统计）'!I:I) | E24: =SUMIF('展示用-2026年签约数据汇总（0702统计）'!C:C,C24,'展示用-2026年签约数据汇总（0702统计）'!J:J) | F24: =SUMIF('展示用-2026年签约数据汇总（0702统计）'!C:C,C24,'展示用-2026年签约数据汇总（0702统计）'!K:K) | G24: =SUMIF('展示用-2026年签约数据汇总（0702统计）'!C:C,C24,'展示用-2026年签约数据汇总（0702统计）'!L:L) | H24: =SUMIF('展示用-2026年签约数据汇总（0702统计）'!C:C,C24,'展示用-2026年签约数据汇总（0702统计）'!M:M) | I24: =SUMIF('展示用-2026年签约数据汇总（0702统计）'!C:C,C24,'展示用-2026年签约数据汇总（0702统计）'!N:N) | P24: =SUM(D24:O24)
B25: 外贸组 | C25: 彭绍佳 | D25: =SUMIF('展示用-2026年签约数据汇总（0702统计）'!C:C,C25,'展示用-2026年签约数据汇总（0702统计）'!I:I) | E25: =SUMIF('展示用-2026年签约数据汇总（0702统计）'!C:C,C25,'展示用-2026年签约数据汇总（0702统计）'!J:J) | F25: =SUMIF('展示用-2026年签约数据汇总（0702统计）'!C:C,C25,'展示用-2026年签约数据汇总（0702统计）'!K:K) | G25: =SUMIF('展示用-2026年签约数据汇总（0702统计）'!C:C,C25,'展示用-2026年签约数据汇总（0702统计）'!L:L) | H25: =SUMIF('展示用-2026年签约数据汇总（0702统计）'!C:C,C25,'展示用-2026年签约数据汇总（0702统计）'!M:M) | I25: =SUMIF('展示用-2026年签约数据汇总（0702统计）'!C:C,C25,'展示用-2026年签约数据汇总（0702统计）'!N:N) | P25: =SUM(D25:O25)
B26: 总计 | D26: =SUM(D5:D25) | E26: =SUM(E5:E25) | F26: =SUM(F5:F25) | G26: =SUM(G5:G25) | H26: =SUM(H5:H25) | I26: =SUM(I5:I25) | J26: =SUM(J5:J25) | K26: =SUM(K5:K25) | ... P26: =SUM(P5:P25)
B46: 小组合计 | C46: 勇哥组 | D46: =SUM(D5:D9) | F46: =SUM(F5:F9) | G46: =SUM(G5:G9) | H46: =SUM(H5:H9) | I46: =SUM(I5:I9) | J46: =SUM(J5:J9) | K46: =SUM(K5:K9) | L46: =SUM(L5:L9) | M46: =SUM(M5:M9) | ... O46: =SUM(O5:O9) | P46: =SUM(D46:O46)
C47: 傲翔组 | D47: =SUM(D15:D18) | F47: =SUM(F15:F18) | G47: =SUM(G15:G18) | H47: =SUM(H15:H18) | I47: =SUM(I15:I18) | J47: =SUM(J15:J18) | K47: =SUM(K15:K18) | L47: =SUM(L15:L18) | M47: =SUM(M15:M18) | ... O47: =SUM(O15:O18) | P47: =SUM(D47:O47)
C48: 意林组 | D48: =SUM(D19:D22) | F48: =SUM(F19:F22) | G48: =SUM(G19:G22) | H48: =SUM(H19:H22) | I48: =SUM(I19:I22) | J48: =SUM(J19:J22) | K48: =SUM(K19:K22) | L48: =SUM(L19:L22) | M48: =SUM(M19:M22) | ... O48: =SUM(O19:O22) | P48: =SUM(D48:O48)
C49: 冉哥组 | D49: =D23 | F49: =F23 | G49: =G23 | H49: =H23 | I49: =I23 | J49: =J23 | K49: =K23 | L49: =L23 | M49: =M23 | ... O49: =O23 | P49: =SUM(D49:O49)
C50: 王安祥组 | D50: =D24 | F50: =F24 | G50: =G24 | H50: =H24 | I50: =I24 | J50: =J24 | K50: =K24 | L50: =L24 | M50: =M24 | ... O50: =O24 | P50: =SUM(D50:O50)
C51: 外贸组 | D51: =D25 | F51: =F25 | G51: =G25 | H51: =H25 | I51: =I25 | J51: =J25 | K51: =K25 | L51: =L25 | M51: =M25 | ... O51: =O25 | P51: =SUM(D51:O51)
C52: 总计 | D52: =SUM(D46:D51) | F52: =SUM(F46:F51) | G52: =SUM(G46:G51) | H52: =SUM(H46:H51) | I52: =SUM(I46:I51) | J52: =SUM(J46:J51) | K52: =SUM(K46:K51) | L52: =SUM(L46:L51) | M52: =SUM(M46:M51) | ... O52: =SUM(O46:O51) | P52: =SUM(D52:O52)
B55: 超元力销售奖惩:
B56: 月度销冠且达80万奖励1000，季度销冠且达240万奖励2000，年度销冠且达800万奖励1万
B57: 月度和季度业绩对赌
B58: 破蛋奖：前2个月能开单，200
B59: 新人达标奖：前2个月完成转正指标，600
B60: 新人业绩奖：0-6月任何月完成30万，500
B61: 转正指标：10万利润或28万业绩
B62: 惩罚：当月未达月度目标，扣除当月业绩提成20%

Sheet 展示用-2026年回款数据汇总(0702统计)
A1: 2026年回款数据汇总
A2: 姓名 | B2: 收款主体 | C2: 付款主体 | D2: 产品 | E2: 合同日期 | F2: 合同总价 | G2: 居间费 | H2: 已回款-提成口（26年以前） | I2: 已回款-提成口径（26年） | J2: 已回款-提成口径总额 | K2: 待回款额 | L2: 已开发票金额 | M2: 已开票未回款 | N2: 回款比例 | O2: 税/运费 | P2: 预计剩余回款时间及金额 | Q2: 备注 | R2: 已回款-业绩口径(26年)
R3: 1月 | S3: 2月 | T3: 3月 | U3: 4月 | V3: 5月 | W3: 6月 | X3: 7月 | Y3: 8月 | Z3: 9月 | AA3: 10月 | AB3: 11月 | AC3: 12月
A4: 吴傲翔 | B4: 庄志勇 | E4: 46054 | F4: 18700 | G4: / | H4: / | I4: =SUM(R4:AC4) | J4: =SUM(H4:I4) | K4: =F4-J4 | L4: 63000 | N4: =IFERROR(J4/F4,0) | S4: 18700
D5: 个人小计： | F5: =SUM(F4:F4) | G5: =SUM(G4:G4) | H5: =SUM(H4:H4) | I5: =SUM(I4:I4) | J5: =SUM(J4:J4) | K5: =SUM(K4:K4) | L5: =SUM(L4:L4) | M5: =SUM(M4:M4) | N5: =IFERROR(J5/F5,0) | O5: =SUM(O4:O4) | R5: =SUM(R4:R4) | S5: =SUM(S4:S4) | T5: =SUM(T4:T4) | U5: =SUM(U4:U4) | V5: =SUM(V4:V4) | W5: =SUM(W4:W4) | X5: =SUM(X4:X4) | Y5: =SUM(Y4:Y4) | ... AC5: =SUM(AC4:AC4)
D7: 部门总计： | F7: =F5 | G7: =G5 | H7: =H5 | I7: =I5 | J7: =J5 | K7: =K5 | L7: =L5 | M7: =M5 | N7: =IFERROR(J7/F7,0) | O7: =O5 | P7: =P5 | Q7: =Q5 | R7: =R5 | S7: =S5 | T7: =T5 | U7: =U5 | V7: =V5 | ... AC7: =AC5
F9: =F7 | G9: =G7 | H9: =H7 | I9: =I7 | J9: =J7 | K9: =K7 | L9: =L7 | M9: =M7 | ... AC9: =AC7

Sheet 明细
A1: 组别 | B1: 姓名 | C1: 收款主体 | D1: 客户名称 | E1: 产品 | F1: 落地地点 | G1: 客户来源 | H1: 项目状态 | I1: 回款状态 | J1: 跟进情况 | K1: 签约日期 | L1: 签约金额 | M1: 居间费 | N1: 回款日期 | O1: 回款金额 | P1: 回款比例 | Q1: 税费 | R1: 签约年月 | S1: 签约季度 | T1: 签约年度 | U1: 回款年月 | V1: 回款季度 | W1: 回款年度 | X1: 状态
A2: 傲翔组 | B2: 胡佳新 | C2: 广州德纳智谷科技有限公司 | D2: 北京汇融视景科技有限公司 | E2: 甘肃科技馆影片 | G2: 自拓 | H2: 已签约 | K2: 45992 | L2: 20000 | N2: 46006 | O2: 20000 | R2: =TEXT(K2,"yyyy-mm") | S2: =YEAR(K2)&"Q"&ROUNDUP(MONTH(K2)/3,0) | T2: =TEXT(K2,"yyyy") | U2: =TEXT(N2,"yyyy-mm") | V2: =YEAR(N2)&"Q"&ROUNDUP(MONTH(N2)/3,0) | W2: =YEAR(N2) | X2: =IF(O2=0,"未回款",IF(SUMIF(E:E,E2,O:O)=L2,"已回款","部分回款"))
